mixemy/__init__.py
mixemy/exceptions/__init__.py
mixemy/models/__init__.py
mixemy/models/_audit.py
mixemy/models/_base.py
mixemy/models/_id.py
mixemy/models/_id_audit.py
mixemy/py.typed
mixemy/repositories/__init__.py
mixemy/repositories/_asyncio.py
mixemy/repositories/_sync.py
mixemy/repositories/permission_strategies/__init__.py
mixemy/repositories/permission_strategies/_base.py
mixemy/repositories/permission_strategies/_factory.py
mixemy/repositories/permission_strategies/_loose_strategy.py
mixemy/repositories/permission_strategies/_strict_strategy.py
mixemy/schemas/__init__.py
mixemy/schemas/_audit_output.py
mixemy/schemas/_base.py
mixemy/schemas/_id_audit_output.py
mixemy/schemas/_id_output.py
mixemy/schemas/_input.py
mixemy/schemas/_output.py
mixemy/schemas/paginations/__init__.py
mixemy/schemas/paginations/_audit.py
mixemy/schemas/paginations/_base.py
mixemy/schemas/paginations/_order_enums.py
mixemy/services/__init__.py
mixemy/services/_asyncio.py
mixemy/services/_sync.py
mixemy/types/__init__.py
mixemy/types/_models.py
mixemy/types/_repositories.py
mixemy/types/_schemas.py
mixemy/types/_services.py
mixemy/utils/__init__.py
mixemy/utils/_convertors.py
mixemy/utils/_utils.py
mixemy/utils/_uuids.py
mixemy-0.13.2.dist-info/METADATA
mixemy-0.13.2.dist-info/WHEEL
mixemy-0.13.2.dist-info/licenses/LICENSE
mixemy-0.13.2.dist-info/RECORD
