Metadata-Version: 2.4
Name: mixemy
Version: 0.13.2
Summary: Mixins for sqlalchemy and pydantic
License: MIT
License-File: LICENSE
Author: Algernon Sampson
Author-email: algiesampson@gmail.com
Requires-Python: >=3.12,<4.0
Classifier: Intended Audience :: Developers
Classifier: License :: OSI Approved :: MIT License
Classifier: Operating System :: OS Independent
Classifier: Programming Language :: Python
Classifier: Programming Language :: Python :: 3
Classifier: Programming Language :: Python :: 3.12
Classifier: Programming Language :: Python :: 3.13
Classifier: Programming Language :: Python :: 3.14
Classifier: Topic :: Database
Classifier: Topic :: Software Development :: Libraries :: Python Modules
Classifier: Typing :: Typed
Provides-Extra: all
Provides-Extra: asyncio
Requires-Dist: greenlet (>=1) ; extra == "all" or extra == "asyncio"
Requires-Dist: pydantic (>=2.0,<3.0)
Requires-Dist: sqlalchemy (>=2.0,<3.0)
Requires-Dist: uuid-utils (>=0.10,<0.11)
Project-URL: Repository, https://github.com/frostyfeet909/mixemy
